dbl_discoverx-0.0.9.dist-info/licenses/LICENSE
discoverx/__init__.py
discoverx/delta_housekeeping.py
discoverx/discovery.py
discoverx/dx.py
discoverx/explorer.py
discoverx/logging.py
discoverx/msql.py
discoverx/rules.py
discoverx/scanner.py
discoverx/table_info.py
discoverx/version.py
discoverx/common/__init__.py
discoverx/common/helper.py
dbl_discoverx-0.0.9.dist-info/METADATA
dbl_discoverx-0.0.9.dist-info/WHEEL
dbl_discoverx-0.0.9.dist-info/top_level.txt
dbl_discoverx-0.0.9.dist-info/RECORD
