Metadata-Version: 2.4
Name: dbl_discoverx
Version: 0.0.9
Summary: DiscoverX - Map and Search your Lakehouse
Home-page: https://databricks.com/learn/labs
Author: Erni Durdevic, David Tempelmann
Author-email: labs@databricks.com
Classifier: Programming Language :: Python :: 3
Classifier: License :: Other/Proprietary License
Classifier: Operating System :: OS Independent
License-File: LICENSE
Requires-Dist: pyyaml
Provides-Extra: local
Requires-Dist: pyspark>=3.3.0; extra == "local"
Requires-Dist: delta-spark>=2.2.0; extra == "local"
Requires-Dist: pandas<2.0.0; extra == "local"
Requires-Dist: numpy<1.24; extra == "local"
Provides-Extra: test
Requires-Dist: pytest; extra == "test"
Requires-Dist: pylint; extra == "test"
Requires-Dist: black; extra == "test"
Requires-Dist: coverage[toml]; extra == "test"
Requires-Dist: pytest-cov; extra == "test"
Requires-Dist: dbx<0.9,>=0.7; extra == "test"
Dynamic: author
Dynamic: author-email
Dynamic: classifier
Dynamic: description
Dynamic: description-content-type
Dynamic: home-page
Dynamic: license-file
Dynamic: provides-extra
Dynamic: requires-dist
Dynamic: summary
